Metadata-Version: 1.1
Name: peewee-rest-query
Version: 0.1.0
Summary: A rest query request args parser for peewee orm.
Home-page: https://github.com/dracarysX/peewee-rest-query
Author: dracarysX
Author-email: huiquanxiong@gmail.com
License: MIT
Keywords: rest,query,no-sql,parser,peewee
Platform: UNKNOWN
Classifier: Programming Language :: Python :: 2.7
Classifier: Programming Language :: Python :: 3
Classifier: Programming Language :: Python :: 3.4
Classifier: Programming Language :: Python :: 3.5
Classifier: Programming Language :: Python :: 3.6
Classifier: License :: OSI Approved :: MIT License
